jaxrwkv/__init__.py
jaxrwkv/auto.py
jaxrwkv/llm.py
jaxrwkv/rwkv4.py
jaxrwkv/rwkv5.py
jaxrwkv/rwkv5_2.py
jaxrwkv/rwkv6.py
jaxrwkv/rwkv7.py
jaxrwkv/tokenizer.py
jaxrwkv/tok_files/20B_tokenizer.json
jaxrwkv/tok_files/rwkv_vocab_v20230424.txt
jaxrwkv-0.0.1.dist-info/licenses/LICENSE
jaxrwkv-0.0.1.dist-info/METADATA
jaxrwkv-0.0.1.dist-info/WHEEL
jaxrwkv-0.0.1.dist-info/top_level.txt
jaxrwkv-0.0.1.dist-info/RECORD
