Metadata-Version: 2.4
Name: jaxrwkv
Version: 0.0.1
Summary: RWKV in JAX
Author-email: Bidipta Sarkar <bidiptas13@gmail.com>
License-Expression: GPL-3.0-only
Classifier: Programming Language :: Python
Classifier: Programming Language :: Python :: 3
Classifier: Programming Language :: Python :: 3.10
Classifier: Intended Audience :: Developers
Classifier: Intended Audience :: Science/Research
Classifier: Operating System :: OS Independent
Classifier: Topic :: Scientific/Engineering :: Artificial Intelligence
Classifier: Topic :: Software Development :: Libraries :: Python Modules
Requires-Python: >=3.10
License-File: LICENSE
Requires-Dist: jax
Requires-Dist: jaxlib
Requires-Dist: huggingface_hub
Requires-Dist: tokenizers
Requires-Dist: einops
Requires-Dist: torch
Requires-Dist: importlib_resources
Provides-Extra: cuda12
Requires-Dist: jax[cuda12]<0.6.0; extra == "cuda12"
Provides-Extra: macos
Requires-Dist: jax==0.5.0; extra == "macos"
Requires-Dist: jax-metal; extra == "macos"
Provides-Extra: testing
Requires-Dist: rwkv; extra == "testing"
Requires-Dist: transformers; extra == "testing"
Requires-Dist: ninja; extra == "testing"
Requires-Dist: tyro; extra == "testing"
Requires-Dist: optax; extra == "testing"
Dynamic: license-file
